bridge_mcp_ghidra.py
iflow_mcp_lauriewired_ghidramcp-1.0.1.dist-info/METADATA
iflow_mcp_lauriewired_ghidramcp-1.0.1.dist-info/WHEEL
iflow_mcp_lauriewired_ghidramcp-1.0.1.dist-info/entry_points.txt
iflow_mcp_lauriewired_ghidramcp-1.0.1.dist-info/licenses/LICENSE
iflow_mcp_lauriewired_ghidramcp-1.0.1.dist-info/RECORD
