Metadata-Version: 2.4
Name: iflow-mcp_lauriewired_ghidramcp
Version: 1.0.1
Summary: MCP server for Ghidra reverse engineering tool integration
License-File: LICENSE
Requires-Python: >=3.10
Requires-Dist: mcp<2,>=1.2.0
Requires-Dist: requests<3,>=2
